auto_py_torrent/__init__.py
auto_py_torrent/__version__.py
auto_py_torrent/auto_py_torrent.py
auto_py_torrent-1.0.8.dist-info/DESCRIPTION.rst
auto_py_torrent-1.0.8.dist-info/METADATA
auto_py_torrent-1.0.8.dist-info/RECORD
auto_py_torrent-1.0.8.dist-info/WHEEL
auto_py_torrent-1.0.8.dist-info/entry_points.txt
auto_py_torrent-1.0.8.dist-info/metadata.json
auto_py_torrent-1.0.8.dist-info/top_level.txt
