Metadata-Version: 2.0
Name: auto-py-torrent
Version: 1.0.8
Summary: Automated tool for file downloads, using torrent or magnet.
Home-page: https://github.com/ocslegna/auto_py_torrent
Author: Gabriel Scotillo
Author-email: gabrielscotillo@gmail.com
License: MIT
Keywords: automate torrent torrent downloads
Platform: UNKNOWN
Classifier: Development Status :: 3 - Alpha
Classifier: Environment :: Console
Classifier: Intended Audience :: End Users/Desktop
Classifier: Intended Audience :: Developers
Classifier: License :: OSI Approved :: MIT License
Classifier: Natural Language :: English
Classifier: Programming Language :: Python :: 3
Classifier: Programming Language :: Python :: 3.3
Classifier: Programming Language :: Python :: 3.4
Classifier: Programming Language :: Python :: 3.5
Classifier: Programming Language :: Python :: 3.6
Classifier: Topic :: Terminals
Requires-Python: >=3
Requires-Dist: beautifulsoup4 (>=4)
Requires-Dist: coloredlogs (>=7.1)
Requires-Dist: lxml
Requires-Dist: requests (>=2.18.1)
Requires-Dist: tabulate (>=0.7.7)
